transparent_overlay/__init__.py
transparent_overlay/core.py
transparent_overlay-2.8.0.dist-info/licenses/LICENSE
transparent_overlay-2.8.0.dist-info/METADATA
transparent_overlay-2.8.0.dist-info/WHEEL
transparent_overlay-2.8.0.dist-info/top_level.txt
transparent_overlay-2.8.0.dist-info/RECORD
