Metadata-Version: 2.4
Name: transparent-overlay
Version: 2.8.0
Summary: High-performance transparent graphics overlay for Windows
Author-email: Илья Яковенко <ilya.a.yakovenko@gmail.com>
License: MIT
Keywords: overlay,graphics,transparent,windows,gdi,hud,performance
Classifier: Development Status :: 4 - Beta
Classifier: Intended Audience :: Developers
Classifier: License :: OSI Approved :: MIT License
Classifier: Operating System :: Microsoft :: Windows
Classifier: Programming Language :: Python :: 3
Classifier: Programming Language :: Python :: 3.7
Classifier: Programming Language :: Python :: 3.8
Classifier: Programming Language :: Python :: 3.9
Classifier: Programming Language :: Python :: 3.10
Classifier: Programming Language :: Python :: 3.11
Classifier: Programming Language :: Python :: 3.12
Classifier: Programming Language :: Python :: 3.13
Classifier: Programming Language :: Python :: 3.14
Requires-Python: >=3.7
License-File: LICENSE
Requires-Dist: numpy>=1.19.0
Requires-Dist: Pillow>=8.0.0
Requires-Dist: pywin32>=300; sys_platform == "win32"
Requires-Dist: numba>=0.56.0
Provides-Extra: examples
Requires-Dist: psutil>=5.8.0; extra == "examples"
Requires-Dist: pyautogui>=0.9.0; extra == "examples"
Requires-Dist: matplotlib>=3.10.8; extra == "examples"
Requires-Dist: opencv-contrib-python>=4.5.0; extra == "examples"
Requires-Dist: mss>=3.0.0; extra == "examples"
Dynamic: license-file
